README.md
setup.py
financialanalysis/__init__.py
financialanalysis/nlptools.py
financialanalysis/utils.py
financialanalysis.egg-info/PKG-INFO
financialanalysis.egg-info/SOURCES.txt
financialanalysis.egg-info/dependency_links.txt
financialanalysis.egg-info/entry_points.txt
financialanalysis.egg-info/requires.txt
financialanalysis.egg-info/top_level.txt